orep/__init__.py
orep/__main__.py
orep/orep.py
orep-1.0.0.dist-info/LICENSE
orep-1.0.0.dist-info/METADATA
orep-1.0.0.dist-info/WHEEL
orep-1.0.0.dist-info/top_level.txt
orep-1.0.0.dist-info/RECORD
