Metadata-Version: 2.1
Name: orep
Version: 1.0.0
Summary: Create, update, and manage host credentials with 1Password
Home-page: https://github.com/qdeslandes/orep
Author: Quentin Deslandes
Author-email: qdeslandes@naccy.de
Classifier: Programming Language :: Python :: 3
Classifier: License :: OSI Approved :: MIT License
Classifier: Operating System :: OS Independent
Requires-Python: >=3.6
License-File: LICENSE
